LICENSE
README.md
setup.py
caesar_rock.egg-info/PKG-INFO
caesar_rock.egg-info/SOURCES.txt
caesar_rock.egg-info/dependency_links.txt
caesar_rock.egg-info/requires.txt
caesar_rock.egg-info/top_level.txt
caesarrock/__init__.py
caesarrock/pore_pressure_grad.py
caesarrock/rockstrengthlog.py
caesarrock/ucs.py