Metadata-Version: 2.1
Name: caesar-rock
Version: 0.0.10
Summary: Package for estimating the confined compressive strength of rock.
Author: LCCV/UFAL
Author-email: erasmo.bezerra@lccv.ufal.br
License: MIT
License-File: LICENSE
